{
  "ok": true,
  "scrapedFrom": "https://multimovies.city/movies/vanilla-sky/",
  "meta": {
    "title": "Vanilla Sky",
    "poster": "https://image.tmdb.org/t/p/w500/cAh2pCiNPftsY3aSqJuIOde7uWr.jpg",
    "synopsis": "David Aames has it all: wealth, good looks and gorgeous women on his arm. But just as he begins falling for the warmhearted Sofia, his face is horribly disfigured in a car accident. That\u2019s just the beginning of his troubles as the lines between illusion and reality, between life and death, are blurred."
  },
  "seasons": [],
  "cast": [],
  "gallery": [],
  "similar": [],
  "views": 0,
  "sources": [],
  "options": [],
  "cache": false,
  "last_update": "2025-09-16 14:29:20"
}